trnslator
